a3mongo/__init__.py
a3mongo/mongo_client_factory.py
a3mongo/mongo_table.py
a3mongo-0.3.0.dist-info/LICENSE
a3mongo-0.3.0.dist-info/METADATA
a3mongo-0.3.0.dist-info/WHEEL
a3mongo-0.3.0.dist-info/top_level.txt
a3mongo-0.3.0.dist-info/RECORD
