Metadata-Version: 2.1
Name: a3mongo
Version: 0.3.0
Summary: a3mongo is a simple wrapper around pymongo to make it easier to use.
Author-email: three-kinds <3179158552@qq.com>
License: MIT
Project-URL: Homepage, https://github.com/three-kinds/a3mongo
Project-URL: Source, https://github.com/three-kinds/a3mongo
Classifier: Development Status :: 2 - Pre-Alpha
Classifier: Intended Audience :: Developers
Classifier: License :: OSI Approved :: MIT License
Classifier: Operating System :: OS Independent
Classifier: Programming Language :: Python
Classifier: Programming Language :: Python :: 3
Classifier: Programming Language :: Python :: 3 :: Only
Classifier: Programming Language :: Python :: 3.10
Classifier: Programming Language :: Python :: 3.11
Classifier: Programming Language :: Python :: 3.12
Classifier: Programming Language :: Python :: 3.13
Classifier: Topic :: Software Development :: Libraries :: Python Modules
Requires-Python: >=3.10
License-File: LICENSE
Requires-Dist: pymongo
